cerium/__init__.py
cerium/androiddriver.py
cerium/by.py
cerium/commands.py
cerium/elements.py
cerium/exceptions.py
cerium/intent.py
cerium/keys.py
cerium/service.py
cerium/utils.py
cerium/executable/AdbWinApi.dll
cerium/executable/AdbWinUsbApi.dll
cerium/executable/adb.exe
cerium-1.2.6.dist-info/LICENSE
cerium-1.2.6.dist-info/METADATA
cerium-1.2.6.dist-info/NOTICE
cerium-1.2.6.dist-info/WHEEL
cerium-1.2.6.dist-info/top_level.txt
cerium-1.2.6.dist-info/RECORD
