Metadata-Version: 2.1
Name: cerium
Version: 1.2.6
Summary: An Android automation framework.
Home-page: https://github.com/ffujiawei/cerium
Author: White Turing
Author-email: fujiawei@stu.hznu.edu.cn
License: Apache 2.0
Keywords: android,adb,automation,testing
Platform: Windows
Classifier: Intended Audience :: Developers
Classifier: License :: OSI Approved :: Apache Software License
Classifier: Operating System :: Microsoft :: Windows
Classifier: Programming Language :: Python :: 3.6
Classifier: Programming Language :: Python :: 3.7
Classifier: Programming Language :: Python :: Implementation :: CPython
Classifier: Programming Language :: Python :: Implementation :: PyPy
Classifier: Topic :: Software Development :: Testing
Classifier: Topic :: Software Development :: Libraries
Requires-Python: >=3.6.0
Requires-Dist: lxml (>=4.2.1)
